README.rst
setup.py
py_lib/__init__.py
py_lib/noise_floor.py
py_lib.egg-info/PKG-INFO
py_lib.egg-info/SOURCES.txt
py_lib.egg-info/dependency_links.txt
py_lib.egg-info/entry_points.txt
py_lib.egg-info/requires.txt
py_lib.egg-info/top_level.txt