Metadata-Version: 1.1
Name: py-lib
Version: 2.0
Summary: My python library where you could find my miscellaneous python codes
Home-page: https://github.com/amanabt/pylib
Author: Aman Abhishek Tiwari
Author-email: amanabt@iitk.ac.in
License: GPLv3+
Keywords: utilities
Platform: any
Classifier: Development Status :: 3 - Alpha
Classifier: Intended Audience :: Science/Research
Classifier: Intended Audience :: Education
Classifier: Topic :: Scientific/Engineering
Classifier: License :: OSI Approved :: GNU General Public License v3 or later (GPLv3+)
Classifier: Programming Language :: Python :: 3.5
Classifier: Operating System :: OS Independent
Classifier: Natural Language :: English
Classifier: Environment :: Console
